lancify/__init__.py
lancify/converter.py
lancify-0.1.0.dist-info/METADATA
lancify-0.1.0.dist-info/WHEEL
lancify-0.1.0.dist-info/entry_points.txt
lancify-0.1.0.dist-info/top_level.txt
lancify-0.1.0.dist-info/RECORD
