Metadata-Version: 2.1
Name: lancify
Version: 0.1.0
Summary: A Python package for converting image datasets to Lance format
Author: Vipul Maheshwari
Author-email: vim.code.level@gmail.com
Classifier: Programming Language :: Python :: 3
Classifier: License :: OSI Approved :: MIT License
Classifier: Operating System :: OS Independent
Requires-Dist: pyarrow
Requires-Dist: pandas
Requires-Dist: tqdm
Requires-Dist: pillow
Requires-Dist: pylance
Requires-Dist: lancedb
